exceptions.py
json_conf_autoref.py
tests/__init__.py
tests/test_001.py
tests/test_002.py
tests/test_003.py
json_conf_autoref-0.1.51.dist-info/LICENSE
json_conf_autoref-0.1.51.dist-info/METADATA
json_conf_autoref-0.1.51.dist-info/WHEEL
json_conf_autoref-0.1.51.dist-info/top_level.txt
json_conf_autoref-0.1.51.dist-info/RECORD
