Metadata-Version: 2.1
Name: json-conf-autoref
Version: 0.1.51
Summary: JSON config parser with variable reference's handler
Home-page: https://github.com/bang/json-conf-autoref
Author: Andre Carneiro
Author-email: andregarciacarneiro@gmail.com
License: UNKNOWN
Project-URL: Bug Tracker, https://github.com/bang/json-conf-autoref/issues
Project-URL: Documentation, https://github.com/bang/json-conf-autoref/blob/master/README.md
Project-URL: Source Code, https://github.com/bang/json-conf-autoref
Keywords: config json variable reference
Platform: UNKNOWN
Classifier: License :: OSI Approved :: Python Software Foundation License
